{
  "mode": "paper",
  "balance_quote": 801.5543766347157,
  "position": {
    "side": "long",
    "amount": 2.790150294607059,
    "entry_price": 71.82,
    "stop_loss": 71.2184078964562,
    "take_profit": 72.72238815531568,
    "opened_at": "2026-06-28T09:00:02.315080+00:00",
    "symbol": "SOL/USD"
  },
  "trade_log": [
    {
      "side": "buy",
      "amount": 2.8129395218002817,
      "price": 71.1,
      "timestamp": "2026-06-28T08:23:54.253779+00:00",
      "reason": "Trend omhoog: EMA5>13, RSI=67.5",
      "pnl_quote": null,
      "symbol": "SOL/USD"
    },
    {
      "side": "sell",
      "amount": 2.8129395218002817,
      "price": 71.79072611705179,
      "timestamp": "2026-06-28T08:50:53.040118+00:00",
      "reason": "Take-profit geraakt (high=72.06 >= 71.79)",
      "pnl_quote": 1.942970793394636,
      "symbol": "SOL/USD"
    },
    {
      "side": "buy",
      "amount": 2.790150294607059,
      "price": 71.82,
      "timestamp": "2026-06-28T09:00:02.315096+00:00",
      "reason": "Trend omhoog: EMA5>13, RSI=74.0",
      "pnl_quote": null,
      "symbol": "SOL/USD"
    }
  ],
  "last_price": 71.68,
  "last_updated": "2026-06-28T09:29:06.658641+00:00"
}